pymysql-stubs/METADATA.toml
pymysql-stubs/__init__.pyi
pymysql-stubs/_auth.pyi
pymysql-stubs/charset.pyi
pymysql-stubs/connections.pyi
pymysql-stubs/converters.pyi
pymysql-stubs/cursors.pyi
pymysql-stubs/err.pyi
pymysql-stubs/optionfile.pyi
pymysql-stubs/protocol.pyi
pymysql-stubs/py.typed
pymysql-stubs/times.pyi
pymysql-stubs/constants/CLIENT.pyi
pymysql-stubs/constants/COMMAND.pyi
pymysql-stubs/constants/CR.pyi
pymysql-stubs/constants/ER.pyi
pymysql-stubs/constants/FIELD_TYPE.pyi
pymysql-stubs/constants/FLAG.pyi
pymysql-stubs/constants/SERVER_STATUS.pyi
pymysql-stubs/constants/__init__.pyi
types_pymysql-1.1.0.20250914.dist-info/licenses/LICENSE
types_pymysql-1.1.0.20250914.dist-info/METADATA
types_pymysql-1.1.0.20250914.dist-info/WHEEL
types_pymysql-1.1.0.20250914.dist-info/top_level.txt
types_pymysql-1.1.0.20250914.dist-info/RECORD
